[
    {
        "ECG": 105,
        "P": -0.125,
        "Q": -0.38,
        "R": 1.155,
        "S": -0.585,
        "T": -0.16,
        "RR": 0.7111111111111111,
        "QT": -1.1111111111111112,
        "QRS": 0.11388888888888889,
        "HR": 84.375,
        "Class": "N"
      },
      {
        "ECG": 105,
        "P": -0.17,
        "Q": -0.335,
        "R": 1.18,
        "S": -0.545,
        "T": -0.19,
        "RR": 0.7138888888888889,
        "QT": -1.1083333333333334,
        "QRS": 0.10277777777777777,
        "HR": 84.04669260700389,
        "Class": "N"
      },
      {
        "ECG": 105,
        "P": -0.105,
        "Q": -0.315,
        "R": 1.235,
        "S": -0.515,
        "T": -0.18,
        "RR": 0.7138888888888889,
        "QT": -1.113888888888889,
        "QRS": 0.1111111111111111,
        "HR": 84.04669260700389,
        "Class": "N"
      },
      {
        "ECG": 105,
        "P": -0.13,
        "Q": -0.315,
        "R": 1.21,
        "S": -0.505,
        "T": -0.155,
        "RR": 0.7305555555555555,
        "QT": -1.1222222222222222,
        "QRS": 0.10833333333333334,
        "HR": 82.12927756653993,
        "Class": "N"
      },
      {
        "ECG": 105,
        "P": -0.075,
        "Q": -0.325,
        "R": 1.205,
        "S": -0.51,
        "T": -0.135,
        "RR": 0.7611111111111111,
        "QT": -1.15,
        "QRS": 0.1111111111111111,
        "HR": 78.83211678832117,
        "Class": "N"
      },
      {
        "ECG": 105,
        "P": -0.075,
        "Q": -0.335,
        "R": 1.205,
        "S": -0.555,
        "T": -0.155,
        "RR": 0.7527777777777778,
        "QT": -1.1777777777777778,
        "QRS": 0.12222222222222222,
        "HR": 79.70479704797049,
        "Class": "N"
      },
      {
        "ECG": 105,
        "P": -0.06,
        "Q": -0.345,
        "R": 1.28,
        "S": -0.56,
        "T": -0.16,
        "RR": 0.7333333333333333,
        "QT": -1.1916666666666667,
        "QRS": 0.11388888888888889,
        "HR": 81.81818181818183,
        "Class": "N"
      },
      {
        "ECG": 105,
        "P": -0.075,
        "Q": -0.34,
        "R": 1.22,
        "S": -0.54,
        "T": -0.19,
        "RR": 0.7,
        "QT": -1.1666666666666667,
        "QRS": 0.11388888888888889,
        "HR": 85.71428571428572,
        "Class": "N"
      },
      {
        "ECG": 105,
        "P": -0.105,
        "Q": -0.295,
        "R": 1.25,
        "S": -0.48,
        "T": -0.16,
        "RR": 0.6944444444444444,
        "QT": -1.1194444444444445,
        "QRS": 0.11388888888888889,
        "HR": 86.4,
        "Class": "N"
      },
      {
        "ECG": 105,
        "P": -0.105,
        "Q": -0.245,
        "R": 1.32,
        "S": -0.435,
        "T": -0.175,
        "RR": 0.6944444444444444,
        "QT": -1.0916666666666666,
        "QRS": 0.1,
        "HR": 86.4,
        "Class": "N"
      },
      {
        "ECG": 105,
        "P": -0.045,
        "Q": -0.28,
        "R": 1.26,
        "S": -0.46,
        "T": -0.11,
        "RR": 0.725,
        "QT": -1.0972222222222223,
        "QRS": 0.09722222222222222,
        "HR": 82.75862068965517,
        "Class": "N"
      },
      {
        "ECG": 105,
        "P": -0.04,
        "Q": -0.27,
        "R": 1.245,
        "S": -0.47,
        "T": -0.1,
        "RR": 0.7555555555555555,
        "QT": -1.1222222222222222,
        "QRS": 0.11666666666666667,
        "HR": 79.41176470588235,
        "Class": "N"
      },
      {
        "ECG": 105,
        "P": -0.01,
        "Q": -0.275,
        "R": 1.235,
        "S": -0.485,
        "T": -0.125,
        "RR": 0.7416666666666667,
        "QT": -1.175,
        "QRS": 0.10833333333333334,
        "HR": 80.89887640449437,
        "Class": "N"
      }
]